setup.py
src/digimat/__init__.py
src/digimat.pdata.egg-info/PKG-INFO
src/digimat.pdata.egg-info/SOURCES.txt
src/digimat.pdata.egg-info/dependency_links.txt
src/digimat.pdata.egg-info/namespace_packages.txt
src/digimat.pdata.egg-info/not-zip-safe
src/digimat.pdata.egg-info/requires.txt
src/digimat.pdata.egg-info/top_level.txt
src/digimat/pdata/__init__.py
src/digimat/pdata/pdata.py