Metadata-Version: 1.0
Name: digimat.pdata
Version: 0.1.1
Summary: Digimat Persistent Data
Home-page: http://www.digimat.ch
Author: Frederic Hess
Author-email: fhess@splust.ch
License: PSF
Platform: UNKNOWN
